{
  "caveats": [],
  "distribution_buckets": [
    {
      "count": 198,
      "label": "<-1m"
    },
    {
      "count": 1359,
      "label": "-1..2m"
    },
    {
      "count": 129,
      "label": "2..5m"
    },
    {
      "count": 19,
      "label": "5..10m"
    },
    {
      "count": 6,
      "label": "10..15m"
    },
    {
      "count": 0,
      "label": "15+m"
    }
  ],
  "heatmap": [
    [
      null,
      null,
      null,
      null,
      null,
      null,
      null,
      null,
      null,
      null,
      null,
      null,
      null,
      null,
      null,
      null,
      null,
      null,
      null
    ],
    [
      null,
      null,
      null,
      null,
      null,
      null,
      null,
      null,
      null,
      null,
      null,
      null,
      null,
      null,
      null,
      null,
      null,
      null,
      null
    ],
    [
      0.2,
      0.2,
      0.2,
      0.2,
      0.8,
      0.7,
      0.1,
      0.0,
      0.2,
      0.6,
      -0.5,
      0.5,
      0.0,
      0.2,
      -0.1,
      0.5,
      0.2,
      0.5,
      -0.8
    ],
    [
      null,
      null,
      null,
      null,
      null,
      null,
      null,
      null,
      null,
      null,
      null,
      null,
      null,
      null,
      null,
      null,
      null,
      null,
      null
    ],
    [
      null,
      null,
      null,
      null,
      null,
      null,
      null,
      null,
      null,
      null,
      null,
      null,
      null,
      null,
      null,
      null,
      null,
      null,
      null
    ],
    [
      null,
      null,
      null,
      null,
      null,
      null,
      null,
      null,
      null,
      null,
      null,
      null,
      null,
      null,
      null,
      null,
      null,
      null,
      null
    ],
    [
      null,
      null,
      null,
      null,
      null,
      null,
      null,
      null,
      null,
      null,
      null,
      null,
      null,
      null,
      null,
      null,
      null,
      null,
      null
    ]
  ],
  "meta": {
    "line_id": "A42",
    "name": "21",
    "type": "bus"
  },
  "per_direction": {
    "0": {
      "distribution_buckets": [
        {
          "count": 198,
          "label": "<-1m"
        },
        {
          "count": 1359,
          "label": "-1..2m"
        },
        {
          "count": 129,
          "label": "2..5m"
        },
        {
          "count": 19,
          "label": "5..10m"
        },
        {
          "count": 6,
          "label": "10..15m"
        },
        {
          "count": 0,
          "label": "15+m"
        }
      ],
      "grade": "A",
      "heatmap": [
        [
          null,
          null,
          null,
          null,
          null,
          null,
          null,
          null,
          null,
          null,
          null,
          null,
          null,
          null,
          null,
          null,
          null,
          null,
          null
        ],
        [
          null,
          null,
          null,
          null,
          null,
          null,
          null,
          null,
          null,
          null,
          null,
          null,
          null,
          null,
          null,
          null,
          null,
          null,
          null
        ],
        [
          0.2,
          0.2,
          0.2,
          0.2,
          0.8,
          0.7,
          0.1,
          0.0,
          0.2,
          0.6,
          -0.5,
          0.5,
          0.0,
          0.2,
          -0.1,
          0.5,
          0.2,
          0.5,
          -0.8
        ],
        [
          null,
          null,
          null,
          null,
          null,
          null,
          null,
          null,
          null,
          null,
          null,
          null,
          null,
          null,
          null,
          null,
          null,
          null,
          null
        ],
        [
          null,
          null,
          null,
          null,
          null,
          null,
          null,
          null,
          null,
          null,
          null,
          null,
          null,
          null,
          null,
          null,
          null,
          null,
          null
        ],
        [
          null,
          null,
          null,
          null,
          null,
          null,
          null,
          null,
          null,
          null,
          null,
          null,
          null,
          null,
          null,
          null,
          null,
          null,
          null
        ],
        [
          null,
          null,
          null,
          null,
          null,
          null,
          null,
          null,
          null,
          null,
          null,
          null,
          null,
          null,
          null,
          null,
          null,
          null,
          null
        ]
      ],
      "median": 0.2,
      "ontime_pct": 84.0,
      "p90": 1.9,
      "sample_n": 1711,
      "score": 91.5,
      "served_pct": 100.0,
      "weekly": [
        {
          "median": 0.2,
          "p90": 1.9,
          "week_start": "2026-06-29"
        }
      ]
    }
  },
  "weekly": [
    {
      "median": 0.2,
      "p90": 1.9,
      "week_start": "2026-06-29"
    }
  ]
}
